updraft/__init__.py
updraft/__main__.py
updraft/version.py
updraft-0.0.1.dist-info/LICENSE
updraft-0.0.1.dist-info/METADATA
updraft-0.0.1.dist-info/WHEEL
updraft-0.0.1.dist-info/top_level.txt
updraft-0.0.1.dist-info/RECORD
